<?xml version="1.0" encoding="UTF-8" standalone="yes"?>
<unit xmlns="http://www.sdml.info/srcML/src" language="Java"
      filename="D:\bio\git\biorimp\BIO-RIMP\test_data\code\jfreechart\src\org\jfree\chart\urls\CustomXYURLGenerator.java">
    <comment type="block">/* ===========================================================
        * JFreeChart : a free chart library for the Java(tm) platform
        * ===========================================================
        *
        * (C) Copyright 2000-2007, by Object Refinery Limited and Contributors.
        *
        * Project Info: http://www.jfree.org/jfreechart/index.html
        *
        * This library is free software; you can redistribute it and/or modify it
        * under the terms of the GNU Lesser General Public License as published by
        * the Free Software Foundation; either version 2.1 of the License, or
        * (at your option) any later version.
        *
        * This library is distributed in the hope that it will be useful, but
        * WITHOUT ANY WARRANTY; without even the implied warranty of MERCHANTABILITY
        * or FITNESS FOR A PARTICULAR PURPOSE. See the GNU Lesser General Public
        * License for more details.
        *
        * You should have received a copy of the GNU Lesser General Public
        * License along with this library; if not, write to the Free Software
        * Foundation, Inc., 51 Franklin Street, Fifth Floor, Boston, MA 02110-1301,
        * USA.
        *
        * [Java is a trademark or registered trademark of Sun Microsystems, Inc.
        * in the United States and other countries.]
        *
        * -------------------------
        * CustomXYURLGenerator.java
        * -------------------------
        * (C) Copyright 2002-2007, by Richard Atkinson and Contributors.
        *
        * Original Author: Richard Atkinson;
        * Contributors: David Gilbert (for Object Refinery Limited);
        *
        * Changes:
        * --------
        * 05-Aug-2002 : Version 1, contributed by Richard Atkinson;
        * 09-Oct-2002 : Fixed errors reported by Checkstyle (DG);
        * 23-Mar-2003 : Implemented Serializable (DG);
        * 20-Jan-2005 : Minor Javadoc update (DG);
        * ------------- JFREECHART 1.0.x ---------------------------------------------
        * 02-Feb-2007 : Removed author tags from all over JFreeChart sources (DG);
        *
        */
    </comment>

    <package>package
        <name><name>org</name>.<name>jfree</name>.<name>chart</name>.
            <name>urls</name>
        </name>
        ;
    </package>

    <import>import
        <name><name>java</name>.<name>io</name>.
            <name>Serializable</name>
        </name>
        ;
    </import>
    <import>import
        <name><name>java</name>.<name>util</name>.
            <name>ArrayList</name>
        </name>
        ;
    </import>
    <import>import
        <name><name>java</name>.<name>util</name>.
            <name>List</name>
        </name>
        ;
    </import>

    <import>import
        <name><name>org</name>.<name>jfree</name>.<name>data</name>.<name>xy</name>.
            <name>XYDataset</name>
        </name>
        ;
    </import>

    <comment type="javadoc">/**
        * A custom URL generator.
        */
    </comment>
    <class>
        <specifier>public</specifier>
        class <name>CustomXYURLGenerator</name>
        <super>
            <implements>implements <name>XYURLGenerator</name>,
                <name>Serializable</name>
            </implements>
        </super>
        <block>{

            <comment type="javadoc">/** For serialization. */</comment>
            <decl_stmt>
                <decl>
                    <type>
                        <specifier>private</specifier>
                        <specifier>static</specifier>
                        <specifier>final</specifier>
                        <name>long</name>
                    </type>
                    <name>serialVersionUID</name> =
                    <init>
                        <expr>-8565933356596551832L</expr>
                    </init>
                </decl>
                ;
            </decl_stmt>

            <comment type="javadoc">/** Storage for the URLs. */</comment>
            <decl_stmt>
                <decl>
                    <type>
                        <specifier>private</specifier>
                        <name>ArrayList</name>
                    </type>
                    <name>urlSeries</name> =
                    <init>
                        <expr>new
                            <call>
                                <name>ArrayList</name>
                                <argument_list>()</argument_list>
                            </call>
                        </expr>
                    </init>
                </decl>
                ;
            </decl_stmt>

            <comment type="javadoc">/**
                * Default constructor.
                */
            </comment>
            <constructor>
                <specifier>public</specifier>
                <name>CustomXYURLGenerator</name>
                <parameter_list>()</parameter_list>
                <block>{
                    <expr_stmt>
                        <expr>
                            <call>
                                <name>super</name>
                                <argument_list>()</argument_list>
                            </call>
                        </expr>
                        ;
                    </expr_stmt>
                    }
                </block>
            </constructor>

            <comment type="javadoc">/**
                * Returns the number of URL lists stored by the renderer.
                *
                * @return The list count.
                */
            </comment>
            <function>
                <type>
                    <specifier>public</specifier>
                    <name>int</name>
                </type>
                <name>getListCount</name>
                <parameter_list>()</parameter_list>
                <block>{
                    <return>return
                        <expr>
                            <call>
                                <name><name>this</name>.<name>urlSeries</name>.
                                    <name>size</name>
                                </name>
                                <argument_list>()</argument_list>
                            </call>
                        </expr>
                        ;
                    </return>
                    }
                </block>
            </function>

            <comment type="javadoc">/**
                * Returns the number of URLs in a given list.
                *
                * @param list the list index (zero based).
                *
                * @return The URL count.
                */
            </comment>
            <function>
                <type>
                    <specifier>public</specifier>
                    <name>int</name>
                </type>
                <name>getURLCount</name>
                <parameter_list>(
                    <param>
                        <decl>
                            <type>
                                <name>int</name>
                            </type>
                            <name>list</name>
                        </decl>
                    </param>
                    )
                </parameter_list>
                <block>{
                    <decl_stmt>
                        <decl>
                            <type>
                                <name>int</name>
                            </type>
                            <name>result</name> =
                            <init>
                                <expr>0</expr>
                            </init>
                        </decl>
                        ;
                    </decl_stmt>
                    <decl_stmt>
                        <decl>
                            <type>
                                <name>List</name>
                            </type>
                            <name>urls</name> =
                            <init>
                                <expr>(<name>List</name>)
                                    <call>
                                        <name><name>this</name>.<name>urlSeries</name>.
                                            <name>get</name>
                                        </name>
                                        <argument_list>(
                                            <argument>
                                                <expr>
                                                    <name>list</name>
                                                </expr>
                                            </argument>
                                            )
                                        </argument_list>
                                    </call>
                                </expr>
                            </init>
                        </decl>
                        ;
                    </decl_stmt>
                    <if>if
                        <condition>(
                            <expr>
                                <name>urls</name>
                                !=
                                <name>null</name>
                            </expr>
                            )
                        </condition>
                        <then>
                            <block>{
                                <expr_stmt>
                                    <expr>
                                        <name>result</name>
                                        =
                                        <call>
                                            <name><name>urls</name>.
                                                <name>size</name>
                                            </name>
                                            <argument_list>()</argument_list>
                                        </call>
                                    </expr>
                                    ;
                                </expr_stmt>
                                }
                            </block>
                        </then>
                    </if>
                    <return>return
                        <expr>
                            <name>result</name>
                        </expr>
                        ;
                    </return>
                    }
                </block>
            </function>

            <comment type="javadoc">/**
                * Returns the URL for an item.
                *
                * @param series the series index.
                * @param item the item index.
                *
                * @return The URL (possibly &lt;code&gt;null&lt;/code&gt;).
                */
            </comment>
            <function>
                <type>
                    <specifier>public</specifier>
                    <name>String</name>
                </type>
                <name>getURL</name>
                <parameter_list>(
                    <param>
                        <decl>
                            <type>
                                <name>int</name>
                            </type>
                            <name>series</name>
                        </decl>
                    </param>
                    ,
                    <param>
                        <decl>
                            <type>
                                <name>int</name>
                            </type>
                            <name>item</name>
                        </decl>
                    </param>
                    )
                </parameter_list>
                <block>{
                    <decl_stmt>
                        <decl>
                            <type>
                                <name>String</name>
                            </type>
                            <name>result</name> =
                            <init>
                                <expr>
                                    <name>null</name>
                                </expr>
                            </init>
                        </decl>
                        ;
                    </decl_stmt>
                    <if>if
                        <condition>(
                            <expr>
                                <name>series</name>
                                &lt;
                                <call>
                                    <name>getListCount</name>
                                    <argument_list>()</argument_list>
                                </call>
                            </expr>
                            )
                        </condition>
                        <then>
                            <block>{
                                <decl_stmt>
                                    <decl>
                                        <type>
                                            <name>List</name>
                                        </type>
                                        <name>urls</name> =
                                        <init>
                                            <expr>(<name>List</name>)
                                                <call>
                                                    <name><name>this</name>.<name>urlSeries</name>.
                                                        <name>get</name>
                                                    </name>
                                                    <argument_list>(
                                                        <argument>
                                                            <expr>
                                                                <name>series</name>
                                                            </expr>
                                                        </argument>
                                                        )
                                                    </argument_list>
                                                </call>
                                            </expr>
                                        </init>
                                    </decl>
                                    ;
                                </decl_stmt>
                                <if>if
                                    <condition>(
                                        <expr>
                                            <name>urls</name>
                                            !=
                                            <name>null</name>
                                        </expr>
                                        )
                                    </condition>
                                    <then>
                                        <block>{
                                            <if>if
                                                <condition>(
                                                    <expr>
                                                        <name>item</name>
                                                        &lt;
                                                        <call>
                                                            <name><name>urls</name>.
                                                                <name>size</name>
                                                            </name>
                                                            <argument_list>()</argument_list>
                                                        </call>
                                                    </expr>
                                                    )
                                                </condition>
                                                <then>
                                                    <block>{
                                                        <expr_stmt>
                                                            <expr>
                                                                <name>result</name>
                                                                = (<name>String</name>)
                                                                <call>
                                                                    <name><name>urls</name>.
                                                                        <name>get</name>
                                                                    </name>
                                                                    <argument_list>(
                                                                        <argument>
                                                                            <expr>
                                                                                <name>item</name>
                                                                            </expr>
                                                                        </argument>
                                                                        )
                                                                    </argument_list>
                                                                </call>
                                                            </expr>
                                                            ;
                                                        </expr_stmt>
                                                        }
                                                    </block>
                                                </then>
                                            </if>
                                            }
                                        </block>
                                    </then>
                                </if>
                                }
                            </block>
                        </then>
                    </if>
                    <return>return
                        <expr>
                            <name>result</name>
                        </expr>
                        ;
                    </return>
                    }
                </block>
            </function>

            <comment type="javadoc">/**
                * Generates a URL.
                *
                * @param dataset the dataset.
                * @param series the series (zero-based index).
                * @param item the item (zero-based index).
                *
                * @return A string containing the URL (possibly &lt;code&gt;null&lt;/code&gt;).
                */
            </comment>
            <function>
                <type>
                    <specifier>public</specifier>
                    <name>String</name>
                </type>
                <name>generateURL</name>
                <parameter_list>(
                    <param>
                        <decl>
                            <type>
                                <name>XYDataset</name>
                            </type>
                            <name>dataset</name>
                        </decl>
                    </param>
                    ,
                    <param>
                        <decl>
                            <type>
                                <name>int</name>
                            </type>
                            <name>series</name>
                        </decl>
                    </param>
                    ,
                    <param>
                        <decl>
                            <type>
                                <name>int</name>
                            </type>
                            <name>item</name>
                        </decl>
                    </param>
                    )
                </parameter_list>
                <block>{
                    <return>return
                        <expr>
                            <call>
                                <name>getURL</name>
                                <argument_list>(
                                    <argument>
                                        <expr>
                                            <name>series</name>
                                        </expr>
                                    </argument>
                                    ,
                                    <argument>
                                        <expr>
                                            <name>item</name>
                                        </expr>
                                    </argument>
                                    )
                                </argument_list>
                            </call>
                        </expr>
                        ;
                    </return>
                    }
                </block>
            </function>

            <comment type="javadoc">/**
                * Adds a list of URLs.
                *
                * @param urls the list of URLs.
                */
            </comment>
            <function>
                <type>
                    <specifier>public</specifier>
                    <name>void</name>
                </type>
                <name>addURLSeries</name>
                <parameter_list>(
                    <param>
                        <decl>
                            <type>
                                <name>List</name>
                            </type>
                            <name>urls</name>
                        </decl>
                    </param>
                    )
                </parameter_list>
                <block>{
                    <expr_stmt>
                        <expr>
                            <call>
                                <name><name>this</name>.<name>urlSeries</name>.
                                    <name>add</name>
                                </name>
                                <argument_list>(
                                    <argument>
                                        <expr>
                                            <name>urls</name>
                                        </expr>
                                    </argument>
                                    )
                                </argument_list>
                            </call>
                        </expr>
                        ;
                    </expr_stmt>
                    }
                </block>
            </function>

            <comment type="javadoc">/**
                * Tests if this object is equal to another.
                *
                * @param o the other object.
                *
                * @return A boolean.
                */
            </comment>
            <function>
                <type>
                    <specifier>public</specifier>
                    <name>boolean</name>
                </type>
                <name>equals</name>
                <parameter_list>(
                    <param>
                        <decl>
                            <type>
                                <name>Object</name>
                            </type>
                            <name>o</name>
                        </decl>
                    </param>
                    )
                </parameter_list>
                <block>{

                    <if>if
                        <condition>(
                            <expr>
                                <name>o</name>
                                ==
                                <name>null</name>
                            </expr>
                            )
                        </condition>
                        <then>
                            <block>{
                                <return>return <expr>false</expr>;
                                </return>
                                }
                            </block>
                        </then>
                    </if>
                    <if>if
                        <condition>(
                            <expr>
                                <name>o</name>
                                ==
                                <name>this</name>
                            </expr>
                            )
                        </condition>
                        <then>
                            <block>{
                                <return>return <expr>true</expr>;
                                </return>
                                }
                            </block>
                        </then>
                    </if>

                    <if>if
                        <condition>(
                            <expr>!(<name>o</name>
                                <name>instanceof</name>
                                <name>CustomXYURLGenerator</name>)
                            </expr>
                            )
                        </condition>
                        <then>
                            <block>{
                                <return>return <expr>false</expr>;
                                </return>
                                }
                            </block>
                        </then>
                    </if>
                    <decl_stmt>
                        <decl>
                            <type>
                                <name>CustomXYURLGenerator</name>
                            </type>
                            <name>generator</name> =
                            <init>
                                <expr>(<name>CustomXYURLGenerator</name>)
                                    <name>o</name>
                                </expr>
                            </init>
                        </decl>
                        ;
                    </decl_stmt>
                    <decl_stmt>
                        <decl>
                            <type>
                                <name>int</name>
                            </type>
                            <name>listCount</name> =
                            <init>
                                <expr>
                                    <call>
                                        <name>getListCount</name>
                                        <argument_list>()</argument_list>
                                    </call>
                                </expr>
                            </init>
                        </decl>
                        ;
                    </decl_stmt>
                    <if>if
                        <condition>(
                            <expr>
                                <name>listCount</name>
                                !=
                                <call>
                                    <name><name>generator</name>.
                                        <name>getListCount</name>
                                    </name>
                                    <argument_list>()</argument_list>
                                </call>
                            </expr>
                            )
                        </condition>
                        <then>
                            <block>{
                                <return>return <expr>false</expr>;
                                </return>
                                }
                            </block>
                        </then>
                    </if>

                    <for>for (
                        <init>
                            <decl>
                                <type>
                                    <name>int</name>
                                </type>
                                <name>series</name> =
                                <init>
                                    <expr>0</expr>
                                </init>
                            </decl>
                            ;
                        </init>
                        <condition>
                            <expr>
                                <name>series</name>
                                &lt;
                                <name>listCount</name>
                            </expr>
                            ;
                        </condition>
                        <incr>
                            <expr><name>series</name>++
                            </expr>
                        </incr>
                        )
                        <block>{
                            <decl_stmt>
                                <decl>
                                    <type>
                                        <name>int</name>
                                    </type>
                                    <name>urlCount</name> =
                                    <init>
                                        <expr>
                                            <call>
                                                <name>getURLCount</name>
                                                <argument_list>(
                                                    <argument>
                                                        <expr>
                                                            <name>series</name>
                                                        </expr>
                                                    </argument>
                                                    )
                                                </argument_list>
                                            </call>
                                        </expr>
                                    </init>
                                </decl>
                                ;
                            </decl_stmt>
                            <if>if
                                <condition>(
                                    <expr>
                                        <name>urlCount</name>
                                        !=
                                        <call>
                                            <name><name>generator</name>.
                                                <name>getURLCount</name>
                                            </name>
                                            <argument_list>(
                                                <argument>
                                                    <expr>
                                                        <name>series</name>
                                                    </expr>
                                                </argument>
                                                )
                                            </argument_list>
                                        </call>
                                    </expr>
                                    )
                                </condition>
                                <then>
                                    <block>{
                                        <return>return <expr>false</expr>;
                                        </return>
                                        }
                                    </block>
                                </then>
                            </if>

                            <for>for (
                                <init>
                                    <decl>
                                        <type>
                                            <name>int</name>
                                        </type>
                                        <name>item</name> =
                                        <init>
                                            <expr>0</expr>
                                        </init>
                                    </decl>
                                    ;
                                </init>
                                <condition>
                                    <expr>
                                        <name>item</name>
                                        &lt;
                                        <name>urlCount</name>
                                    </expr>
                                    ;
                                </condition>
                                <incr>
                                    <expr><name>item</name>++
                                    </expr>
                                </incr>
                                )
                                <block>{
                                    <decl_stmt>
                                        <decl>
                                            <type>
                                                <name>String</name>
                                            </type>
                                            <name>u1</name> =
                                            <init>
                                                <expr>
                                                    <call>
                                                        <name>getURL</name>
                                                        <argument_list>(
                                                            <argument>
                                                                <expr>
                                                                    <name>series</name>
                                                                </expr>
                                                            </argument>
                                                            ,
                                                            <argument>
                                                                <expr>
                                                                    <name>item</name>
                                                                </expr>
                                                            </argument>
                                                            )
                                                        </argument_list>
                                                    </call>
                                                </expr>
                                            </init>
                                        </decl>
                                        ;
                                    </decl_stmt>
                                    <decl_stmt>
                                        <decl>
                                            <type>
                                                <name>String</name>
                                            </type>
                                            <name>u2</name> =
                                            <init>
                                                <expr>
                                                    <call>
                                                        <name><name>generator</name>.
                                                            <name>getURL</name>
                                                        </name>
                                                        <argument_list>(
                                                            <argument>
                                                                <expr>
                                                                    <name>series</name>
                                                                </expr>
                                                            </argument>
                                                            ,
                                                            <argument>
                                                                <expr>
                                                                    <name>item</name>
                                                                </expr>
                                                            </argument>
                                                            )
                                                        </argument_list>
                                                    </call>
                                                </expr>
                                            </init>
                                        </decl>
                                        ;
                                    </decl_stmt>
                                    <if>if
                                        <condition>(
                                            <expr>
                                                <name>u1</name>
                                                !=
                                                <name>null</name>
                                            </expr>
                                            )
                                        </condition>
                                        <then>
                                            <block>{
                                                <if>if
                                                    <condition>(
                                                        <expr>!
                                                            <call>
                                                                <name><name>u1</name>.
                                                                    <name>equals</name>
                                                                </name>
                                                                <argument_list>(
                                                                    <argument>
                                                                        <expr>
                                                                            <name>u2</name>
                                                                        </expr>
                                                                    </argument>
                                                                    )
                                                                </argument_list>
                                                            </call>
                                                        </expr>
                                                        )
                                                    </condition>
                                                    <then>
                                                        <block>{
                                                            <return>return <expr>false</expr>;
                                                            </return>
                                                            }
                                                        </block>
                                                    </then>
                                                </if>
                                                }
                                            </block>
                                        </then>
                                        <else>else
                                            <block>{
                                                <if>if
                                                    <condition>(
                                                        <expr>
                                                            <name>u2</name>
                                                            !=
                                                            <name>null</name>
                                                        </expr>
                                                        )
                                                    </condition>
                                                    <then>
                                                        <block>{
                                                            <return>return <expr>false</expr>;
                                                            </return>
                                                            }
                                                        </block>
                                                    </then>
                                                </if>
                                                }
                                            </block>
                                        </else>
                                    </if>
                                    }
                                </block>
                            </for>
                            }
                        </block>
                    </for>
                    <return>return <expr>true</expr>;
                    </return>

                    }
                </block>
            </function>

            }
        </block>
    </class>
</unit>
